aplus_auth/__init__.py
aplus_auth/apps.py
aplus_auth/exceptions.py
aplus_auth/payload.py
aplus_auth/requests.py
aplus_auth/auth/__init__.py
aplus_auth/auth/django.py
aplus_auth/management/commands/__init__.py
aplus_auth/management/commands/gentoken.py
aplus_auth-0.2.3.dist-info/METADATA
aplus_auth-0.2.3.dist-info/WHEEL
aplus_auth-0.2.3.dist-info/top_level.txt
aplus_auth-0.2.3.dist-info/RECORD
