Metadata-Version: 2.1
Name: aplus-auth
Version: 0.2.3
Summary: Authorization library for A+ services
Home-page: https://github.com/apluslms/aplus-auth
Author: A+ LMS
Author-email: aplusguru@cs.aalto.fi
Project-URL: Bug Tracker, https://github.com/apluslms/aplus-auth/issues
Classifier: Programming Language :: Python :: 3
Classifier: Programming Language :: Python :: 3.7
Classifier: Programming Language :: Python :: 3.8
Classifier: Programming Language :: Python :: 3.9
Classifier: Programming Language :: Python :: 3.10
Classifier: Operating System :: OS Independent
Requires-Python: >=3.7
Requires-Dist: PyJWT[crypto] (>=1.0.1)
Provides-Extra: requests
Requires-Dist: requests (>=2.25.1) ; extra == 'requests'
